pyf.station-2.0.5-py2.7-nspkg.pth
pyf.station-2.0.5.dist-info/DESCRIPTION.rst
pyf.station-2.0.5.dist-info/top_level.txt
pyf.station-2.0.5.dist-info/METADATA
pyf.station-2.0.5.dist-info/RECORD
pyf.station-2.0.5.dist-info/WHEEL
pyf.station-2.0.5.dist-info/metadata.json
pyf.station-2.0.5.dist-info/namespace_packages.txt
pyf.station-2.0.5.dist-info/entry_points.txt
pyf/station/main.py
pyf/station/client.py
pyf/station/utils.py
pyf/station/__init__.py
