Metadata-Version: 2.0
Name: pyf.station
Version: 2.0.5
Summary: PyF.Station is a protocol with client and server implementation to transfer python generators accross tcp networks.
Home-page: http://pyfproject.org
Author: UNKNOWN
Author-email: UNKNOWN
License: MIT
Keywords: python generator tcp/ip
Platform: UNKNOWN
Classifier: Programming Language :: Python
Requires-Dist: setuptools
Requires-Dist: twisted
Requires-Dist: pyf.transport (>=2.0)
Requires-Dist: pyjon.events
Requires-Dist: simplejson
